globality_black/__init__.py
globality_black/black_handler.py
globality_black/blank_lines.py
globality_black/cli.py
globality_black/common.py
globality_black/comprehensions.py
globality_black/constants.py
globality_black/diff.py
globality_black/dotted_chains.py
globality_black/jupyter_formatter.py
globality_black/reformat_text.py
globality_black/tuples.py
globality_black-2023.46.126.dist-info/LICENSE
globality_black-2023.46.126.dist-info/METADATA
globality_black-2023.46.126.dist-info/WHEEL
globality_black-2023.46.126.dist-info/entry_points.txt
globality_black-2023.46.126.dist-info/top_level.txt
globality_black-2023.46.126.dist-info/RECORD
