Metadata-Version: 2.1
Name: globality-black
Version: 2023.46.126
Summary: A wrapper for black adding new features
Home-page: https://github.com/globality-corp/globality-black
Author: Globality AI
Author-email: ai@globality.com
Keywords: globality_black,black,python,formatter
Classifier: Programming Language :: Python :: 3
Classifier: Programming Language :: Python :: 3.7
Classifier: Programming Language :: Python :: 3.8
Classifier: Programming Language :: Python :: 3.9
Requires-Python: >=3.7
License-File: LICENSE
Requires-Dist: Click
Requires-Dist: parso
Requires-Dist: pytest >=3
Requires-Dist: black >=22.1.0
Requires-Dist: pexpect
Provides-Extra: jupyter
Requires-Dist: jupyterlab-code-formatter ; extra == 'jupyter'
Provides-Extra: lint
Requires-Dist: flake8-isort >=4.1.1 ; extra == 'lint'
Requires-Dist: flake8-print >=4.0.0 ; extra == 'lint'
Requires-Dist: flake8-logging-format ; extra == 'lint'
Requires-Dist: globality-black ; extra == 'lint'
Provides-Extra: test
Requires-Dist: pytest ; extra == 'test'
Requires-Dist: pytest-cov ; extra == 'test'
Provides-Extra: typehinting
Requires-Dist: mypy ; extra == 'typehinting'
Requires-Dist: types-setuptools ; extra == 'typehinting'
